md-footer/__init__.py
md-footer/main.py
md_footer/__init__.py
md_footer/main.py
md_footer-0.1.1.dist-info/LICENSE
md_footer-0.1.1.dist-info/METADATA
md_footer-0.1.1.dist-info/WHEEL
md_footer-0.1.1.dist-info/entry_points.txt
md_footer-0.1.1.dist-info/top_level.txt
md_footer-0.1.1.dist-info/RECORD
