Metadata-Version: 2.1
Name: md_footer
Version: 0.1.1
Summary: Manage and append consistent or dynamic footers to your Markdown files with md-footer, a versatile CLI tool.
Home-page: https://github.com/glizzykingdreko/md-footer
Author: GlizzyKingDreko
Author-email: glizzykingdreko@protonmail.com
Keywords: markdown,footer,documentation,markdown-footer,cli-tool,automation,md-footer,markdown-tool,append-footer,markdown-automation
Classifier: Programming Language :: Python :: 3
Classifier: License :: OSI Approved :: MIT License
Classifier: Operating System :: OS Independent
Requires-Python: >=3.6
License-File: LICENSE
